{
    "word": "drops",
    "phonetic": "drɒp",
    "type": "n., n., v.",
    "meaning": "gouttes goutte; bonbon; chute tomber; laisser tomber; baisser; descendre en parachute; annuler; abandonner",
    "details": "<C><F><I><N><span style=\"color:#c00000\">n.</span> gouttes</N></I></F></C><C><F><H><span style=\"color:#009900\">drɒp</span></H><I><N><span style=\"color:#c00000\">n.</span> goutte; bonbon; chute</N></I><I><N><span style=\"color:#c00000\">v.</span> tomber; laisser tomber; baisser; descendre en parachute; annuler; abandonner</N></I></F></C>"
}