{
    "word": "cashed",
    "phonetic": "kæʃ",
    "type": "adj., n., v.",
    "meaning": "einkassiert Bargeld einlösen (Scheck), eintauschen (Scheck); profitieren; viel Geld gewinnen",
    "details": "<C><F><I><N><span style=\"color:#c00000\">adj.</span> einkassiert</N></I></F></C><C><F><H><span style=\"color:#009900\">kæʃ</span></H><I><N><span style=\"color:#c00000\">n.</span> Bargeld</N></I><I><N><span style=\"color:#c00000\">v.</span> einlösen (Scheck), eintauschen (Scheck); profitieren; viel Geld gewinnen</N></I></F></C>"
}