{
    "word": "circumvolution",
    "phonetic": "[͵sɜ:kəmvəʹlu:ʃ(ə)n]",
    "type": "n, спец.",
    "meaning": "1.извилина, изгиб2.1) вращение2) оборот, поворот3.1) окольный путь, уловка2) околичность4. плоская спираль",
    "details": "<C><F><H><L>circumvolution</L></H><I><N><x K=\"#0000D0\"><v>[͵sɜ:kəmvəʹlu:ʃ(ə)n]</v></x><br /><x K=\"#A0A0A0\"><em><x K=\"#C00000\">n</x></em></x><br /><Í> 1.  извилина, изгиб <br /> 2.  1) вращение <br /> 2) оборот, поворот <br /> 3.  1) окольный путь, уловка <br /> 2) околичность <br /> 4.  <x K=\"#A0A0A0\"><em><x K=\"#C00000\">спец.</x> </em></x>плоская спираль <br /> </Í></N></I></F></C>"
}