{
    "word": "damnatory",
    "phonetic": "[ʹdæmnət(ə)rı]",
    "type": "a",
    "meaning": "1.осуждающий2.вызывающий осуждение; пагубный, губительный",
    "details": "<C><F><H><L>damnatory</L></H><I><N><x K=\"#0000D0\"><v>[ʹdæmnət(ə)rı]</v></x><br /><x K=\"#A0A0A0\"><em><x K=\"#C00000\">a</x></em></x><br /><Í> 1.  осуждающий <br />  <x K=\"#009999\">damnatory view of smth. - резко отрицательное /весьма нелестное/ мнение о чём-л., осуждение чего-л. </x><br /> 2.  вызывающий осуждение; пагубный, губительный <br />  <x K=\"#009999\">damnatory weakness - губительная слабость </x><br />  <x K=\"#009999\">damnatory evidence - компрометирующие факты, дискредитирующие сведения </x><br /> </Í></N></I></F></C>"
}