{
    "word": "embrown",
    "phonetic": "[ımʹbraʋn]",
    "type": "v, редк., поэт.",
    "meaning": "1.1) делать коричневым, смуглым; покрывать загаром2) загорать, смуглеть2. покрываться мглой, мраком",
    "details": "<C><F><H><L>embrown</L></H><I><N><x K=\"#0000D0\"><v>[ımʹbraʋn]</v></x><br /><x K=\"#A0A0A0\"><em><x K=\"#C00000\">v</x></em></x><br /><Í> 1.  <x K=\"#A0A0A0\"><em><x K=\"#C00000\">редк.</x> </em></x><br /> 1) делать коричневым, смуглым; покрывать загаром <br /> 2) загорать, смуглеть <br /> 2.  <x K=\"#A0A0A0\"><em><x K=\"#C00000\">поэт.</x> </em></x>покрываться мглой, мраком <br />  <x K=\"#009999\">air embrowned with shadows - меркнущий свет, угасающий день </x><br /> </Í></N></I></F></C>"
}