{
    "word": "pintable",
    "phonetic": "[ʹpın͵teıb(ə)l]",
    "type": "n, см., тж.",
    "meaning": "стенд или автомат для игры в пинбол pinball 2",
    "details": "<C><F><H><L>pintable</L></H><I><N><x K=\"#0000D0\"><v>[ʹpın͵teıb(ə)l]</v></x><br /><x K=\"#A0A0A0\"><em><x K=\"#C00000\">n</x></em></x><br /><Í> стенд <x K=\"#A0A0A0\"><em>или</em></x> автомат для игры в пинбол <x K=\"#0000D0\"><v>[<x K=\"#A0A0A0\"><em><x K=\"#C00000\">см.</x> <x K=\"#C00000\">тж.</x> </em></x>pinball 2]</v></x>  <br /> </Í></N></I></F></C>"
}