{
    "word": "smut",
    "phonetic": "[smʌt]",
    "type": "n, и т. п., и т. п., горн., v",
    "meaning": "1.частица угольной пыли, сажи2.сажа 3.грязное, чёрное пятно 4.непристойностьto talk smut - говорить сальности; рассказывать неприличные анекдоты5.головня (болезнь растений) 6. землистый уголь 1.пачкать, чернить, коптить 2.1) заражать головнёй (растения) 2) заражаться головнёй (о растениях)",
    "details": "<C><F><H><L>smut</L></H><I><N><strong>1.</strong> <x K=\"#0000D0\"><v>[smʌt]</v></x> <x K=\"#A0A0A0\"><em><x K=\"#C00000\">n</x></em></x><br /><Í>  1.  частица угольной пыли, сажи <x K=\"#A0A0A0\"><em><x K=\"#C00000\">и т. п.</x> </em></x><br />  2.  сажа <br />  3.  грязное, чёрное пятно <br />  4.  непристойность <br />   <x K=\"#009999\">to talk smut - говорить сальности; рассказывать неприличные анекдоты <x K=\"#A0A0A0\"><em><x K=\"#C00000\">и т. п.</x> </em></x></x><br />  5.  головня (<x K=\"#A0A0A0\"><em>болезнь растений</em></x>) <br />  6.  <x K=\"#A0A0A0\"><em><x K=\"#C00000\">горн.</x> </em></x>землистый уголь <br />  </Í><br /><strong>2.</strong> <x K=\"#0000D0\"><v>[smʌt]</v></x> <x K=\"#A0A0A0\"><em><x K=\"#C00000\">v</x></em></x><br /><Í>  1.  пачкать, чернить, коптить <br />  2.  1) заражать головнёй (<x K=\"#A0A0A0\"><em>растения</em></x>) <br />  2) заражаться головнёй (<x K=\"#A0A0A0\"><em>о растениях</em></x>) <br />  </Í></N></I></F></C>"
}