{
    "word": "snag",
    "phonetic": "[snæg]",
    "type": "n, и т. п., разг., и т. п., разг., v, и т. п., лес., разг., и т. п.",
    "meaning": "1.сук, сучок 2.коряга, топляк 3.нарост, шишка (на дереве ) 4.выступ 5. snaggletooth 6.отросток, короткая ветвь рога у оленя 7. неожиданное препятствие или затруднение 8.1) неровный разрыв, дыра 2) спущенная петля, затяжка (на чулке ) 9. 1) кусок2) куча, масса1.налететь на корягу 2.очищать от коряг, сучьев, топляков (реку ) 3. срезать крупные сучья, оставляя сучки 4.создавать препятствия, затруднения; застопорить 5. поймать, перехватитьto snag a football pass - перехватить пас, прервать передачу (футбол)6.зацепить, порвать (чулок )",
    "details": "<C><F><H><L>snag</L></H><I><N><strong>1.</strong> <x K=\"#0000D0\"><v>[snæg]</v></x> <x K=\"#A0A0A0\"><em><x K=\"#C00000\">n</x></em></x><br /><Í>  1.  сук, сучок <br />  2.  коряга, топляк <br />  3.  нарост, шишка (<x K=\"#A0A0A0\"><em>на дереве <x K=\"#C00000\">и т. п.</x></em></x>) <br />  4.  выступ <br />  5.  = snaggletooth <br />  6.  отросток, короткая ветвь рога у оленя <br />  7.  <x K=\"#A0A0A0\"><em><x K=\"#C00000\">разг.</x> </em></x>неожиданное препятствие <x K=\"#A0A0A0\"><em>или</em></x> затруднение <br />   <x K=\"#009999\">to strike /to come on, to run against/ a snag - натолкнуться на препятствие </x><br />   <x K=\"#009999\">there was a snag in the talks - в переговорах произошла заминка </x><br />   <x K=\"#009999\">there's the snag! - вот в чём загвоздка! </x><br />   <x K=\"#009999\">there is a snag in it somewhere - здесь есть какой-то подвох </x><br />  8.  1) неровный разрыв, дыра <br />  2) спущенная петля, затяжка (<x K=\"#A0A0A0\"><em>на чулке <x K=\"#C00000\">и т. п.</x></em></x>) <br />  9.  <x K=\"#A0A0A0\"><em><x K=\"#C00000\">разг.</x> </em></x><br />  1) кусок <br />   <x K=\"#009999\">he broke off a snag of bread - он отломил кусок хлеба </x><br />  2) куча, масса <br />   <x K=\"#009999\">he came into a snag of money - ему отвалили кучу денег </x><br />  </Í><br /><strong>2.</strong> <x K=\"#0000D0\"><v>[snæg]</v></x> <x K=\"#A0A0A0\"><em><x K=\"#C00000\">v</x></em></x><br /><Í>  1.  налететь на корягу <br />  2.  очищать от коряг, сучьев, топляков (<x K=\"#A0A0A0\"><em>реку <x K=\"#C00000\">и т. п.</x></em></x>) <br />  3.  <x K=\"#A0A0A0\"><em><x K=\"#C00000\">лес.</x> </em></x>срезать крупные сучья, оставляя сучки <br />  4.  создавать препятствия, затруднения; застопорить <br />   <x K=\"#009999\">the parley is snagged - совещание зашло в тупик </x><br />   <x K=\"#009999\">his hostility snagged all my plans - его враждебное отношение сорвало все мои планы </x><br />  5.  <x K=\"#A0A0A0\"><em><x K=\"#C00000\">разг.</x> </em></x>поймать, перехватить <br />   <x K=\"#009999\">to snag a football pass - перехватить пас, прервать передачу (<x K=\"#A0A0A0\"><em>футбол</em></x>) </x><br />   <x K=\"#009999\">to snag a taxi - поймать такси </x><br />   <x K=\"#009999\">he snagged a cake while his mother was away - он стащил пирожок, пока матери не было </x><br />   <x K=\"#009999\">to snag a rich husband - подцепить богатого мужа </x><br />  6.  зацепить, порвать (<x K=\"#A0A0A0\"><em>чулок <x K=\"#C00000\">и т. п.</x></em></x>) <br />  </Í></N></I></F></C>"
}