{
    "word": "spikenard",
    "phonetic": "[ʹspaıknɑ:d]",
    "type": "n, бот., бот.",
    "meaning": "1. нард (Nardostachys jatamansi)2.нард (ароматическое вещество)3. аралия (Aralia gen.)",
    "details": "<C><F><H><L>spikenard</L></H><I><N><x K=\"#0000D0\"><v>[ʹspaıknɑ:d]</v></x><br /><x K=\"#A0A0A0\"><em><x K=\"#C00000\">n</x></em></x><br /><Í> 1.  <x K=\"#A0A0A0\"><em><x K=\"#C00000\">бот.</x> </em></x>нард (<x K=\"#A0A0A0\"><em>Nardostachys jatamansi</em></x>) <br /> 2.  нард (<x K=\"#A0A0A0\"><em>ароматическое вещество</em></x>) <br /> 3.  <x K=\"#A0A0A0\"><em><x K=\"#C00000\">бот.</x> </em></x>аралия (<x K=\"#A0A0A0\"><em>Aralia gen.</em></x>) <br /> </Í></N></I></F></C>"
}