{
    "word": "topsy-turvy",
    "phonetic": "[͵tɒpsıʹtɜ:vı]",
    "type": "n, a, adv, v",
    "meaning": "беспорядок, неразбериха, кутерьма; ≅ дым коромыслом 1)перевёрнутый вверх дном 2)беспорядочный, хаотичныйвверх дном; шиворот-навыворот1)перевёртывать вверх дном 2)приводить в беспорядок",
    "details": "<C><F><H><L>topsy-turvy</L></H><I><N><strong>1.</strong> <x K=\"#0000D0\"><v>[͵tɒpsıʹtɜ:vı]</v></x> <x K=\"#A0A0A0\"><em><x K=\"#C00000\">n</x></em></x><br /><Í>  беспорядок, неразбериха, кутерьма; ≅ дым коромыслом <br />  </Í><br /><strong>2.</strong> <x K=\"#0000D0\"><v>[͵tɒpsıʹtɜ:vı]</v></x> <x K=\"#A0A0A0\"><em><x K=\"#C00000\">a</x></em></x><br /><Í>  1)  перевёрнутый вверх дном <br />   <x K=\"#009999\">her room was always topsy-turvy - в её комнате всегда всё перевёрнуто вверх дном /вверх тормашками/ </x><br />   <x K=\"#009999\">the whole world was topsy-turvy - всё в мире пошло кувырком /шиворот-навыворот/ </x><br />  2)  беспорядочный, хаотичный <br />   <x K=\"#009999\">a topsy-turvy way of reasoning - путаный ход рассуждений </x><br />  </Í><br /><strong>3.</strong> <x K=\"#0000D0\"><v>[͵tɒpsıʹtɜ:vı]</v></x> <x K=\"#A0A0A0\"><em><x K=\"#C00000\">adv</x></em></x><br /><Í>  вверх дном; шиворот-навыворот <br />   <x K=\"#009999\">to turn topsy-turvy - а) переворачивать вверх дном; делать всё наоборот; б) переворачиваться вверх дном </x><br />  </Í><br /><strong>4.</strong> <x K=\"#0000D0\"><v>[͵tɒpsıʹtɜ:vı]</v></x> <x K=\"#A0A0A0\"><em><x K=\"#C00000\">v</x></em></x><br /><Í>  1)  перевёртывать вверх дном <br />  2)  приводить в беспорядок <br />  </Í></N></I></F></C>"
}