{
    "word": "vindictive",
    "phonetic": "[vınʹdıktıv]",
    "type": "a, редк.",
    "meaning": "1.мстительный2. карательный; карающий3.злопамятный",
    "details": "<C><F><H><L>vindictive</L></H><I><N><x K=\"#0000D0\"><v>[vınʹdıktıv]</v></x><br /><x K=\"#A0A0A0\"><em><x K=\"#C00000\">a</x></em></x><br /><Í> 1.  мстительный <br /> 2.  <x K=\"#A0A0A0\"><em><x K=\"#C00000\">редк.</x> </em></x>карательный; карающий <br />  <x K=\"#009999\">vindictive punishment - возмездие </x><br />  <x K=\"#009999\">vindictive deities - боги-мстители </x><br /> 3.  злопамятный <br /> </Í></N></I></F></C>"
}