{
    "word": "write-up",
    "phonetic": "[ʹraıtʌp]",
    "type": "n, преим., амер., амер., фин., спец.",
    "meaning": "1.1) восхваление в печати; высокая оценка2) искусственное создание имени; рекламирование (кого-л.)2. 1) запись (в учётном регистре), повышающая стоимость2) завышение стоимости активов; приписки3. отчёт, описание; запись (наблюдений)",
    "details": "<C><F><H><L>write-up</L></H><I><N><x K=\"#0000D0\"><v>[ʹraıtʌp]</v></x><br /><x K=\"#A0A0A0\"><em><x K=\"#C00000\">n</x></em></x><br /><Í> 1.  1) <x K=\"#A0A0A0\"><em><x K=\"#C00000\">преим.</x> <x K=\"#C00000\">амер.</x> </em></x>восхваление в печати; высокая оценка <br />  <x K=\"#009999\">the concert got a good write-up in the local newspaper - местная газета поместила хороший отзыв о концерте </x><br /> 2) искусственное создание имени; рекламирование (<x K=\"#A0A0A0\"><em>кого-л.</em></x>) <br /> 2.  <x K=\"#A0A0A0\"><em><x K=\"#C00000\">амер.</x> <x K=\"#C00000\">фин.</x> </em></x><br /> 1) запись (<x K=\"#A0A0A0\"><em>в учётном регистре</em></x>), повышающая стоимость <br /> 2) завышение стоимости активов; приписки <br /> 3.  <x K=\"#A0A0A0\"><em><x K=\"#C00000\">спец.</x> </em></x>отчёт, описание; запись (<x K=\"#A0A0A0\"><em>наблюдений</em></x>) <br /> </Í></N></I></F></C>"
}