{
    "word": "ditch",
    "phonetic": "dɪtʃ",
    "type": "n., v.",
    "meaning": "n. zanja, cárcava, carcavina, chamba, foso, hoya; cuneta; cauce, canalv. abrir zanjas, hacer acequias; abrir zanjas en; rodear con una zanja",
    "details": "<C><F><H><span style=\"color:#009900\">dɪtʃ</span></H><I><N><span style=\"color:#c00000\">n.</span> zanja, cárcava, carcavina, chamba, foso, hoya; cuneta; cauce, canal</N></I><I><N><span style=\"color:#c00000\">v.</span> abrir zanjas, hacer acequias; abrir zanjas en; rodear con una zanja</N></I></F></C>"
}