{
    "word": "stoutest",
    "phonetic": "staʊt",
    "type": "n., adj.",
    "meaning": "n. cerveza negra, cerveza amarga, cerveza de malta, cerveza negra y fuerteadj. corpulento, bien formado, fornido, gordo, grueso, recio, robusto, voluminoso",
    "details": "<C><F><H><span style=\"color:#009900\">staʊt</span></H><I><N><span style=\"color:#c00000\">n.</span> cerveza negra, cerveza amarga, cerveza de malta, cerveza negra y fuerte</N></I><I><N><span style=\"color:#c00000\">adj.</span> corpulento, bien formado, fornido, gordo, grueso, recio, robusto, voluminoso</N></I></F></C>"
}