{
    "word": "wiling",
    "phonetic": "waɪl",
    "type": "n., v.",
    "meaning": "n. artimaña, ardid, astucia, tretav. Cometer un fraude, hacer un ardid, engañar; embaucar; engatusar; portarse con astucia",
    "details": "<C><F><H><span style=\"color:#009900\">waɪl</span></H><I><N><span style=\"color:#c00000\">n.</span> artimaña, ardid, astucia, treta</N></I><I><N><span style=\"color:#c00000\">v.</span> Cometer un fraude, hacer un ardid, engañar; embaucar; engatusar; portarse con astucia</N></I></F></C>"
}