{
    "word": "rule",
    "phonetic": "ruːl",
    "type": "n., v.",
    "meaning": "قاعدة, سلطة, سيطرة, عهد, قاعدة أساس, وضع راهن, مسطرة, قاعدة مبدأ, قانون, دستور, حكم, عرف, عادة  حكم, سيطر, سطر, قرر, أعلن, حكم يدير, ساد, قرر قضائيا",
    "details": "<C><F><H><span style=\"color:#009900\">ruːl</span></H><I><N><Ò><span style=\"color:#c00000\">n.</span>  قاعدة, سلطة, سيطرة, عهد, قاعدة أساس, وضع راهن, مسطرة, قاعدة مبدأ, قانون, دستور, حكم, عرف, عادة</Ò></N></I><I><N><Ò><span style=\"color:#c00000\">v.</span>  حكم, سيطر, سطر, قرر, أعلن, حكم يدير, ساد, قرر قضائيا</Ò></N></I></F></C>"
}