{
    "word": "productions",
    "phonetic": "/production/",
    "type": "danh từ",
    "meaning": "(Econ) Sản xuất.; sự đưa ra, sự trình bày; sự sinh; sản lượng; sự sản xuất, sản phẩm; mass p. sản xuất hàng loạt",
    "details": "<br />- (Econ) Sản xuất.<br />+ Hành động biến đổi các yếu tố sản xuất thành hàng hoá và dịch vụ do yêu cầu của tiêu dùng và đầu tư.</Q></N></I></F></C><C><F><I><N><Q>@production /production/<br />*  danh từ<br />- sự đưa ra, sự trình bày<br />- sự sản xuất, sự chế tạo<br />- sự sinh<br />- sản phẩm, tác phẩm<br />- sản lượng<br />- (từ Mỹ,nghĩa Mỹ) sự bỏ vốn và phương tiện để dựng (phim, kịch...)<br /><br />@production<br />- sự sản xuất, sản phẩm<br />- current p. sự sản xuất hiện hành<br />- mass p. sản xuất hàng loạt"
}