{
    "word": "backsword",
    "phonetic": "back.sword",
    "type": "名词",
    "meaning": "[`æˌ,ˌɒˋæˋɒ,ɒə]名词单刃刀大砍刀木刀供练习击剑用用木刀练习击剑者",
    "details": "<div style=\"margin-bottom:3px\">back.sword</div><div style=\"margin-bottom:3px\"><br /><strong>[bækˌsord, -ˌsɒrd; ˋbækˋsɒ:d, -sɒəd]</strong></div><div style=\"margin-bottom:3px\"><br /><strong>名词</strong></div><div style=\"margin-bottom:3px\">1 单刃刀; 大砍刀</div><div style=\"margin-bottom:3px\">2 木刀 (供练习击剑用)</div><div style=\"margin-bottom:3px\">3 用木刀练习击剑者</div>"
}