{
    "word": "devadasi",
    "phonetic": "de.va.da.si",
    "type": "名词",
    "meaning": "[ˌєə`ɑˌєəˋɑє]名词‘印度’供应神庙舞女之阶级神庙舞女神庙之高等妓女",
    "details": "<div style=\"margin-bottom:3px\">de.va.da.si</div><div style=\"margin-bottom:3px\"><br /><strong>[ˌdєvədɑsZ; ˌdєivəˋdɑ:sє]</strong></div><div style=\"margin-bottom:3px\"><br /><strong>名词</strong></div><div style=\"margin-bottom:3px\">‘印度’</div><div style=\"margin-bottom:3px\">1 供应神庙舞女之阶级</div><div style=\"margin-bottom:3px\">2 神庙舞女</div><div style=\"margin-bottom:3px\">3 神庙之高等妓女</div>"
}