{
    "word": "Freudian",
    "phonetic": "Freud.i.an",
    "type": "形容词, 可数名词",
    "meaning": "[`ɒəˋɒə]《的形容词》形容词佛洛伊德的口语无意识层中关于性的可数名词佛洛伊德学说的信徒",
    "details": "<div style=\"margin-bottom:3px\">Freud.i.an</div><div style=\"margin-bottom:3px\"><br /><strong>[frɒIdIən; ˋfrɒidjən]</strong></div><div style=\"margin-bottom:3px\">《Freud 的形容词》</div><div style=\"margin-bottom:3px\"><br /><strong>形容词</strong></div><div style=\"margin-bottom:3px\">1 佛洛伊德的</div><div style=\"margin-bottom:3px\">2 (口语)无意识层中关于性的</div><div style=\"margin-bottom:3px\"><br /><strong>可数名词</strong></div><div style=\"margin-bottom:3px\">佛洛伊德学说的信徒</div>"
}