{
    "word": "growths",
    "phonetic": "growth",
    "type": "名词",
    "meaning": "[θ^θ]《的名词》名词成长,生长,发育~幼儿期的成长相当快发展,发达~工业的发展[又作~]增大,增加,扩张,扩展~最近十年来,会员逐渐增加栽培,培养[]~植物的栽培[]~外国产[国产]的苹果~自己栽培的水果生长物草木、胡须、指甲等~那一带杂草丛生~他脸上的胡须留了一个礼拜了肿疡,瘤状物~恶性肿瘤~癌肿",
    "details": "<div style=\"margin-bottom:3px\">growth</div><div style=\"margin-bottom:3px\"><br /><strong>[groθ; ^rouθ]</strong></div><div style=\"margin-bottom:3px\">《grow 的名词》</div><div style=\"margin-bottom:3px\"><br /><strong>名词</strong></div><div style=\"margin-bottom:3px\">1 (U)成长,生长,发育</div><div style=\"margin-bottom:3px\">G~ is rapid in infancy.</div><div style=\"margin-bottom:3px\">幼儿期的成长相当快</div><div style=\"margin-bottom:3px\">2 a. (U)发展,发达</div><div style=\"margin-bottom:3px\">industrial ~</div><div style=\"margin-bottom:3px\">工业的发展</div><div style=\"margin-bottom:3px\">b. (U) [又作 a ~] 增大,增加,扩张,扩展</div><div style=\"margin-bottom:3px\">There has been a gradual ~ in membership for the last ten years.</div><div style=\"margin-bottom:3px\">最近十年来,会员逐渐增加</div><div style=\"margin-bottom:3px\">3 (U)栽培,培养[of]</div><div style=\"margin-bottom:3px\">the ~ of a plant</div><div style=\"margin-bottom:3px\">植物的栽培</div><div style=\"margin-bottom:3px\">apples of foreign [home] ~</div><div style=\"margin-bottom:3px\">外国产 [国产] 的苹果</div><div style=\"margin-bottom:3px\">fruits of one's own ~</div><div style=\"margin-bottom:3px\">自己栽培的水果</div><div style=\"margin-bottom:3px\">4 (C)</div><div style=\"margin-bottom:3px\">a. 生长物</div><div style=\"margin-bottom:3px\">(草木、胡须、指甲等)</div><div style=\"margin-bottom:3px\">There was a thick ~ of weeds around there.</div><div style=\"margin-bottom:3px\">那一带杂草丛生</div><div style=\"margin-bottom:3px\">He had a week's ~ of beard on his face.</div><div style=\"margin-bottom:3px\">他脸上的胡须留了一个礼拜了</div><div style=\"margin-bottom:3px\">b. 肿疡,瘤状物</div><div style=\"margin-bottom:3px\">a malignant ~</div><div style=\"margin-bottom:3px\">恶性肿瘤</div><div style=\"margin-bottom:3px\">a cancerous ~</div><div style=\"margin-bottom:3px\">癌肿</div>"
}