{
    "word": "kicks",
    "phonetic": "kick",
    "type": "及物动词, 不及物动词, 名词",
    "meaning": "[]《源自古北欧语“弯膝”的意思》及物动词踢~踢球踢[身体的某部位][,]~踢某人的腹部踢移~踢脱鞋子~把狗踢走~踢倒椅子~踢起石头~踢起一片尘埃~把某人踢赶出去~把某人踢下阶梯把某人赶[撵]出去‘足球’把球踢进[常~]俚戒毒不及物动词[朝…]踢[]~那孩子又踢又哭~[]朝某人[物]踢踢跳于发射时反弹口语[对…]进行无益的反抗[",
    "details": "<div style=\"margin-bottom:3px\">kick</div><div style=\"margin-bottom:3px\"><br /><strong>[kIk; kik]</strong></div><div style=\"margin-bottom:3px\">《源自古北欧语“弯膝”的意思》</div><div style=\"margin-bottom:3px\"><br /><strong>及物动词</strong></div><div style=\"margin-bottom:3px\">1 a. 踢</div><div style=\"margin-bottom:3px\">~ a ball</div><div style=\"margin-bottom:3px\">踢球</div><div style=\"margin-bottom:3px\">b. 踢<人的>[身体的某部位][in, on]</div><div style=\"margin-bottom:3px\">~ a person in the stomach</div><div style=\"margin-bottom:3px\">踢某人的腹部</div><div style=\"margin-bottom:3px\">c. 踢移</div><div style=\"margin-bottom:3px\">~ off one's shoes</div><div style=\"margin-bottom:3px\">踢脱鞋子</div><div style=\"margin-bottom:3px\">~ a dog off</div><div style=\"margin-bottom:3px\">把狗踢走</div><div style=\"margin-bottom:3px\">~ over a chair</div><div style=\"margin-bottom:3px\">踢倒椅子</div><div style=\"margin-bottom:3px\">~ up a stone</div><div style=\"margin-bottom:3px\">踢起石头</div><div style=\"margin-bottom:3px\">~ up a cloud of dust</div><div style=\"margin-bottom:3px\">踢起一片尘埃</div><div style=\"margin-bottom:3px\">~ a person out</div><div style=\"margin-bottom:3px\">把某人 (踢) 赶出去</div><div style=\"margin-bottom:3px\">(cf. kick out</div><div style=\"margin-bottom:3px\">(2)</div><div style=\"margin-bottom:3px\">~ a person downstairs</div><div style=\"margin-bottom:3px\">把某人踢下阶梯; 把某人赶 [撵] 出去</div><div style=\"margin-bottom:3px\">2 ‘足球’把球踢进 <球门></div><div style=\"margin-bottom:3px\">3 [常~ the habit] (俚)戒毒</div><div style=\"margin-bottom:3px\"><br /><strong>不及物动词</strong></div><div style=\"margin-bottom:3px\">1 a. [朝…]踢[at]</div><div style=\"margin-bottom:3px\">The child was ~ing and crying.</div><div style=\"margin-bottom:3px\">那孩子又踢又哭</div><div style=\"margin-bottom:3px\">~ at a person [a thing]</div><div style=\"margin-bottom:3px\">朝某人[物]踢</div><div style=\"margin-bottom:3px\">b. <马>踢跳</div><div style=\"margin-bottom:3px\">c. <枪等> (于发射时) 反弹</div><div style=\"margin-bottom:3px\">2 (口语)</div><div style=\"margin-bottom:3px\">a. [对…]进行 (无益的) 反抗[反对]; 强烈地抗议[at, against]</div><div style=\"margin-bottom:3px\">The farmers ~ed at [against] the government's measure.</div><div style=\"margin-bottom:3px\">农民们强烈地抗议政府的措施</div><div style=\"margin-bottom:3px\">b. [就…]抱怨[about]</div><div style=\"margin-bottom:3px\">~ about poor service</div><div style=\"margin-bottom:3px\">抱怨服务不佳</div><div style=\"margin-bottom:3px\">kick about = kick around</div><div style=\"margin-bottom:3px\">kick against the pricks→prick</div><div style=\"margin-bottom:3px\">kick a man when he's down</div><div style=\"margin-bottom:3px\">(1) 脚踢已倒的人; 落井下石</div><div style=\"margin-bottom:3px\">(2) 趁人之危,趁火打劫</div><div style=\"margin-bottom:3px\">kick around</div><div style=\"margin-bottom:3px\">(1) 粗鲁地使用<东西>; 虐待<某人></div><div style=\"margin-bottom:3px\">(2) 多方地详细讨论 [研讨] <建议等></div><div style=\"margin-bottom:3px\">(3)<人>徘徊; (仍) 活著</div><div style=\"margin-bottom:3px\">(4)<东西>被搁著 [未受注意] ; 可以得到,有</div><div style=\"margin-bottom:3px\">(5) 时常迁居或更换工作; 到处流浪</div><div style=\"margin-bottom:3px\">kick back</div><div style=\"margin-bottom:3px\">(1)[把…]踢回; [对…]还击[at]</div><div style=\"margin-bottom:3px\">(2) 踢回…; 对…还击</div><div style=\"margin-bottom:3px\">(3)(口语) <以钱的一部分> 付回扣</div><div style=\"margin-bottom:3px\">kick in</div><div style=\"margin-bottom:3px\">(1) 把<东西>踢入里面,踢进</div><div style=\"margin-bottom:3px\">~ a ball in</div><div style=\"margin-bottom:3px\">把球踢进</div><div style=\"margin-bottom:3px\">(2) 把<门等> (从外侧) 踢破</div><div style=\"margin-bottom:3px\">~ the door in</div><div style=\"margin-bottom:3px\">踢破门,破门而入</div><div style=\"margin-bottom:3px\">(3)(口语)缴付 <分摊的金额等> ,捐助</div><div style=\"margin-bottom:3px\">kick a person in the teeth</div><div style=\"margin-bottom:3px\">→ tooth</div><div style=\"margin-bottom:3px\">kick off</div><div style=\"margin-bottom:3px\">(1) → v.t. 1 c</div><div style=\"margin-bottom:3px\">(2)(口语)开始 <大会等> ; 发起</div><div style=\"margin-bottom:3px\">(3)‘足球’开球</div><div style=\"margin-bottom:3px\">(4)(口语)<聚会等>开始</div><div style=\"margin-bottom:3px\">(5)(口语)<人>开始 [茶会等] [with]</div><div style=\"margin-bottom:3px\">(6)(美口语)离去</div><div style=\"margin-bottom:3px\">(7)(美口语)死</div><div style=\"margin-bottom:3px\">kick out</div><div style=\"margin-bottom:3px\">(1) → v.t. 1 c</div><div style=\"margin-bottom:3px\">(2)(口语)解雇<人>,炒<某人>鱿鱼; 开除</div><div style=\"margin-bottom:3px\">(3)‘足球’把球踢出界外</div><div style=\"margin-bottom:3px\">kick up</div><div style=\"margin-bottom:3px\">(1) → v.t. 1 c</div><div style=\"margin-bottom:3px\">(2)(口语)引起,惹起 <骚动、混乱等></div><div style=\"margin-bottom:3px\">~up a row [fuss, shindy, stink]</div><div style=\"margin-bottom:3px\">引起一阵骚动 [喧闹]</div><div style=\"margin-bottom:3px\">kick up one's heels</div><div style=\"margin-bottom:3px\">→heel.</div><div style=\"margin-bottom:3px\">kick a person upstairs (</div><div style=\"margin-bottom:3px\">口语)把<人>明升暗降</div><div style=\"margin-bottom:3px\"><br /><strong>名词</strong></div><div style=\"margin-bottom:3px\">1 (C)</div><div style=\"margin-bottom:3px\">a. 踢</div><div style=\"margin-bottom:3px\">give a ~ at</div><div style=\"margin-bottom:3px\">? 踢…一脚</div><div style=\"margin-bottom:3px\">b.‘足球’踢 (球) ; (英)踢者 (kicker)</div><div style=\"margin-bottom:3px\">→free kick,penalty kick</div><div style=\"margin-bottom:3px\">a good ~</div><div style=\"margin-bottom:3px\">擅长踢的选手; 善踢者</div><div style=\"margin-bottom:3px\">c. (发射时的枪等的) 反弹,后坐力</div><div style=\"margin-bottom:3px\">2 (C)(口语)反对,拒绝,抗议 [against,at]</div><div style=\"margin-bottom:3px\">3 [the ~](俚)解雇</div><div style=\"margin-bottom:3px\">get [give a person] the ~(</div><div style=\"margin-bottom:3px\">被) 解雇 [炒鱿鱼]</div><div style=\"margin-bottom:3px\">4 (C)(口语)刺激,兴奋,过瘾 (just) for ~s (只) 为了寻刺激</div><div style=\"margin-bottom:3px\">He gets a ~ out of (reading) a comic book.</div><div style=\"margin-bottom:3px\">他看连环图画书看得津津有味</div><div style=\"margin-bottom:3px\">5(U)(口语) (酒等的) 刺激性,醉人的力量 [劲]</div><div style=\"margin-bottom:3px\">This vodka has a lot of ~ in it.</div><div style=\"margin-bottom:3px\">这伏特加酒很够劲儿</div><div style=\"margin-bottom:3px\">6(U)(口语)弹力,力气</div><div style=\"margin-bottom:3px\">get more kicks than halfpence</div><div style=\"margin-bottom:3px\">得不偿失 [挨踢多于赚半便士]</div><div style=\"margin-bottom:3px\">off a kick (</div><div style=\"margin-bottom:3px\">美俚)再也提不起精神 [兴致索然]</div><div style=\"margin-bottom:3px\">(←→ on a kick)</div><div style=\"margin-bottom:3px\">on a kick (</div><div style=\"margin-bottom:3px\">美俚)正在热中</div><div style=\"margin-bottom:3px\">He's on a yachting ~.</div><div style=\"margin-bottom:3px\">他现在正热中于驾游艇</div>"
}