{
    "word": "logrolling",
    "phonetic": "log.rolling",
    "type": "不可数名词",
    "meaning": "不可数名词滚木材指合力将伐下的圆木滚动到一个地方或河流中水中踩圆木比赛脚踩漂浮、转动不定的圆木,保持身体平衡而不落水美尤指政治上的合作,互助作家同行间等的互相称赞,互相标榜,互相吹捧",
    "details": "<div style=\"margin-bottom:3px\">log.rolling</div><div style=\"margin-bottom:3px\"><br /><strong>不可数名词</strong></div><div style=\"margin-bottom:3px\">1 a. 滚木材</div><div style=\"margin-bottom:3px\">(指合力将伐下的圆木滚动到一个地方或河流中)</div><div style=\"margin-bottom:3px\">b. 水中踩圆木 (比赛)</div><div style=\"margin-bottom:3px\">(脚踩漂浮、转动不定的圆木,保持身体平衡而不落水)</div><div style=\"margin-bottom:3px\">2 (美)</div><div style=\"margin-bottom:3px\">a. (尤指政治上的) 合作,互助</div><div style=\"margin-bottom:3px\">b. (作家同行间等的) 互相称赞,互相标榜,互相吹捧</div>"
}