{
    "word": "lunacies",
    "phonetic": "lu.na.cy",
    "type": "名词",
    "meaning": "[`əˋə]《的名词》名词精神错乱,疯癫,月夜狂[常]愚蠢的行为,疯狂之举",
    "details": "<div style=\"margin-bottom:3px\">lu.na.cy</div><div style=\"margin-bottom:3px\"><br /><strong>[lunəsI; ˋlu:nəsi]</strong></div><div style=\"margin-bottom:3px\">《lunatic 的名词》</div><div style=\"margin-bottom:3px\"><br /><strong>名词</strong></div><div style=\"margin-bottom:3px\">1 (U)精神错乱,疯癫,月夜狂</div><div style=\"margin-bottom:3px\">2 (C) [常 lunacies] 愚蠢的行为,疯狂之举</div>"
}