{
    "word": "marketing",
    "phonetic": "mar.ket.ing",
    "type": "不可数名词",
    "meaning": "不可数名词在市场的交易,买卖美购物~购物‘经济’制造销售,行销学自制造计画至最后销售的全部过程包括市场调查、流通管道、广告等等在内",
    "details": "<div style=\"margin-bottom:3px\">mar.ket.ing</div><div style=\"margin-bottom:3px\"><br /><strong>不可数名词</strong></div><div style=\"margin-bottom:3px\">1 在市场的交易,买卖</div><div style=\"margin-bottom:3px\">2 (美)购物</div><div style=\"margin-bottom:3px\">do one's ~</div><div style=\"margin-bottom:3px\">购物</div><div style=\"margin-bottom:3px\">3‘经济’制造销售,行销 (学)</div><div style=\"margin-bottom:3px\">(自制造计画至最后销售的全部 过程; 包括市场调查、流通管道、广告等等在内)</div>"
}