{
    "word": "moody",
    "phonetic": "mood.y",
    "type": "形容词, 副词, 名词",
    "meaning": "[`ˋ]《的形容词》形容词心情不稳定的不和悦的情绪坏的闷闷不乐的,阴郁的~心情不稳定的人~她有时候闷闷不乐副词名词",
    "details": "<div style=\"margin-bottom:3px\">mood.y</div><div style=\"margin-bottom:3px\"><br /><strong>[mudI; ˋmu:di]</strong></div><div style=\"margin-bottom:3px\">《mood 3 的形容词》</div><div style=\"margin-bottom:3px\"><br /><strong>形容词</strong></div><div style=\"margin-bottom:3px\">(mood.i.er; -i.est)</div><div style=\"margin-bottom:3px\">心情不稳定的; 不和悦的; 情绪坏的; 闷闷不乐的,阴郁的</div><div style=\"margin-bottom:3px\">a ~ person</div><div style=\"margin-bottom:3px\">心情不稳定的人</div><div style=\"margin-bottom:3px\">She is some times ~.</div><div style=\"margin-bottom:3px\">她有时候闷闷不乐</div><div style=\"margin-bottom:3px\"><br /><strong>副词</strong></div><div style=\"margin-bottom:3px\">mood.i.ly</div><div style=\"margin-bottom:3px\">(-dIlI; -dili)</div><div style=\"margin-bottom:3px\"><br /><strong>名词</strong></div><div style=\"margin-bottom:3px\">-i.ness</div>"
}