{
    "word": "opinions",
    "phonetic": "o.pin.ion",
    "type": "名词",
    "meaning": "[ə`əəˋə]《的名词》名词意见,见解~?你对于那件事的意见如何?~依我看来,那是内容无聊的书~根据某些人的看法,美国人心中仍保持著先驱者的拓荒精神【同义字】受个人判断或喜爱与感情影响的意见个人对事物的看法或想法[~]看法,意见,见解~我的看法是,智慧在某种程度内是可以通过教育培植的[常~]所持的论调,主张,信念[]~依照某人",
    "details": "<div style=\"margin-bottom:3px\">o.pin.ion</div><div style=\"margin-bottom:3px\"><br /><strong>[əpInjən; əˋpinjən]</strong></div><div style=\"margin-bottom:3px\">《opine 的名词》</div><div style=\"margin-bottom:3px\"><br /><strong>名词</strong></div><div style=\"margin-bottom:3px\">1 (C)</div><div style=\"margin-bottom:3px\">a. 意见,见解</div><div style=\"margin-bottom:3px\">What is your ~ (of that)?.</div><div style=\"margin-bottom:3px\">你 (对于那件事) 的意见如何?</div><div style=\"margin-bottom:3px\">In my ~ that is a poor book.</div><div style=\"margin-bottom:3px\">依我看来,那是内容无聊的书</div><div style=\"margin-bottom:3px\">In the ~ of some people the pioneer spirit remains in the American mind.</div><div style=\"margin-bottom:3px\">根据某些人的看法,美国人心中仍保持著先驱者的拓荒精神</div><div style=\"margin-bottom:3px\">【同义字】</div><div style=\"margin-bottom:3px\">opinion 受个人判断或喜爱与感情影响的意见</div><div style=\"margin-bottom:3px\">view 个人对事物的看法或想法</div><div style=\"margin-bottom:3px\">b. [be of the ~] <有…的> 看法,意见,见解</div><div style=\"margin-bottom:3px\">I am of the ~ that in some degree wisdom can be taught.</div><div style=\"margin-bottom:3px\">我的看法是,智慧在某种程度内是可以通过教育培植的</div><div style=\"margin-bottom:3px\">c. [常~s] 所持的论调,主张,信念</div><div style=\"margin-bottom:3px\">act up [act according] to one's ~s</div><div style=\"margin-bottom:3px\">依照某人所持的信念去做</div><div style=\"margin-bottom:3px\">2 (U) (对某事的) 一般想法,看法,舆论</div><div style=\"margin-bottom:3px\">public ~</div><div style=\"margin-bottom:3px\">舆论</div><div style=\"margin-bottom:3px\">3 [an ~]</div><div style=\"margin-bottom:3px\">a. (善恶的) 判断,评价</div><div style=\"margin-bottom:3px\">have [form] a bad [low] ~ of</div><div style=\"margin-bottom:3px\">?认为…不好,瞧不起…</div><div style=\"margin-bottom:3px\">have [form] a good [high, favorable] ~ of</div><div style=\"margin-bottom:3px\">?认为…好,对…评价高</div><div style=\"margin-bottom:3px\">b. 好的评价</div><div style=\"margin-bottom:3px\">have no ~ [not much of an ~] of</div><div style=\"margin-bottom:3px\">?认为…不太好; 对…印象不佳</div><div style=\"margin-bottom:3px\">4 (C)专家的意见,鉴定</div><div style=\"margin-bottom:3px\">a medical ~</div><div style=\"margin-bottom:3px\">医师的意见</div><div style=\"margin-bottom:3px\">ask for a second ~</div><div style=\"margin-bottom:3px\">征求别人的意见</div>"
}