{
    "word": "priapus",
    "phonetic": "pri.a.pus",
    "type": "名词",
    "meaning": "[`єəˋєə]名词~普里阿普斯希腊罗马神话中男性生殖之神,为勃起阳具之拟人化象征普里阿普斯之像古代花园中常置,作用类似稻草人阳具之像",
    "details": "<div style=\"margin-bottom:3px\">pri.a.pus</div><div style=\"margin-bottom:3px\"><br /><strong>[praIєpəs; praiˋєipəs]</strong></div><div style=\"margin-bottom:3px\"><br /><strong>名词</strong></div><div style=\"margin-bottom:3px\">1 (P~) 普里阿普斯</div><div style=\"margin-bottom:3px\">(希腊罗马神话中男性生殖之神,为勃起阳具之拟人化象征)</div><div style=\"margin-bottom:3px\">2 普里阿普斯之像</div><div style=\"margin-bottom:3px\">(古代花园中常置,作用类似稻草人)</div><div style=\"margin-bottom:3px\">3 阳具之像</div>"
}