{
    "word": "shuns",
    "phonetic": "shun",
    "type": "及物动词",
    "meaning": "[ʃʌʃʌ]及物动词始终规避~[,]避开与人交往[出名,诱惑]避免…~他避免与他的任何朋友碰面",
    "details": "<div style=\"margin-bottom:3px\">shun</div><div style=\"margin-bottom:3px\"><br /><strong>[ʃʌn; ʃʌn]</strong></div><div style=\"margin-bottom:3px\"><br /><strong>及物动词</strong></div><div style=\"margin-bottom:3px\">(shunned; shun.ning)</div><div style=\"margin-bottom:3px\">1 (始终) 规避</div><div style=\"margin-bottom:3px\">~ company [publicity, temptation]</div><div style=\"margin-bottom:3px\">避开与人交往 [出名,诱惑]</div><div style=\"margin-bottom:3px\">2 避免…</div><div style=\"margin-bottom:3px\">He ~ned meeting any of his friends.</div><div style=\"margin-bottom:3px\">他避免与他的任何朋友碰面</div>"
}