{
    "word": "tartar",
    "phonetic": "tar.tar",
    "type": "不可数名词",
    "meaning": "[`ɑˋɑə]不可数名词酒石酿造葡萄酒时酒桶底的沉淀物质为酒石酸的原料~酒石英牙垢",
    "details": "<div style=\"margin-bottom:3px\">tar.tar</div><div style=\"margin-bottom:3px\"><br /><strong>[tɑrtL; ˋtɑ:tə]</strong></div><div style=\"margin-bottom:3px\"><br /><strong>不可数名词</strong></div><div style=\"margin-bottom:3px\">1 酒石</div><div style=\"margin-bottom:3px\">(酿造葡萄酒时酒桶底的沉淀物质; 为酒石酸的原料)</div><div style=\"margin-bottom:3px\">cream of ~</div><div style=\"margin-bottom:3px\">酒石英</div><div style=\"margin-bottom:3px\">2 牙垢 (scale)</div>"
}