{
    "word": "Vedda",
    "phonetic": "Ved.da",
    "type": "名词, 形容词",
    "meaning": "[`əˋєə]名词亦作维达人斯里兰卡最古老的土著形容词",
    "details": "<div style=\"margin-bottom:3px\">Ved.da</div><div style=\"margin-bottom:3px\"><br /><strong>[vZdə; ˋvєdə]</strong></div><div style=\"margin-bottom:3px\"><br /><strong>名词</strong></div><div style=\"margin-bottom:3px\">亦作 Veddah. 维达人</div><div style=\"margin-bottom:3px\">(斯里兰卡最古老的土著)</div><div style=\"margin-bottom:3px\"><br /><strong>形容词</strong></div><div style=\"margin-bottom:3px\">Ved'doid</div>"
}