{
    "word": "viva",
    "phonetic": "vi.va",
    "type": "感叹词, 名词, 名词",
    "meaning": "[`əˋə]《源自义大利语及西班牙语》感叹词万岁!?!名词叫喊万岁之声[~]欢呼声[`əˋə]名词英口语=",
    "details": "<div style=\"margin-bottom:3px\">vi.va</div><div style=\"margin-bottom:3px\"><br /><strong>[vivə; ˋvi:və]</strong></div><div style=\"margin-bottom:3px\">《源自义大利语及西班牙语》</div><div style=\"margin-bottom:3px\"><br /><strong>感叹词</strong></div><div style=\"margin-bottom:3px\">万岁! (Long live?!)</div><div style=\"margin-bottom:3px\"><br /><strong>名词</strong></div><div style=\"margin-bottom:3px\">1 (C)叫喊万岁之声</div><div style=\"margin-bottom:3px\">2 [~s]欢呼声</div><div style=\"margin-bottom:3px\">vi.va</div><div style=\"margin-bottom:3px\"><br /><strong>[vaIvə; ˋvaivə]</strong></div><div style=\"margin-bottom:3px\"><br /><strong>名词</strong></div><div style=\"margin-bottom:3px\">(英口语)= viva voce</div>"
}