{
    "word": "greying",
    "phonetic": "greɪ",
    "type": "adj., n., v., adj.",
    "meaning": "verzilverd, vergrijsd grijs (kleur) (veelvoorkomend in Brits schrift) vergrijzen (veelvoorkomend in Brits schrift); verzilveren (het haar)(veel voorkomend in Brits schrift) grijs (veelvoorkomend in Brits schrift); verzilverd (veelvoorkomend in Brits schrift)",
    "details": "<C><F><I><N><span style=\"color:#c00000\">adj.</span> verzilverd, vergrijsd</N></I></F></C><C><F><H><span style=\"color:#009900\">greɪ</span></H><I><N><span style=\"color:#c00000\">n.</span> grijs (kleur) (veelvoorkomend in Brits schrift)</N></I><I><N><span style=\"color:#c00000\">v.</span> vergrijzen (veelvoorkomend in Brits schrift); verzilveren (het haar)(veel voorkomend in Brits schrift)</N></I><I><N><span style=\"color:#c00000\">adj.</span> grijs (veelvoorkomend in Brits schrift); verzilverd (veelvoorkomend in Brits schrift)</N></I></F></C>"
}