{
    "word": "handed",
    "phonetic": "hænd",
    "type": "adj., n., v., adj.",
    "meaning": "met hand, handen van-; met....handen hand; handschrift; wijzer; 4 inch; kaarten i.d. hand van kaartspeler; arbeider; matroos aanreiken, doorgeven, geven; helpen handig, v.d. hand",
    "details": "<C><F><I><N><span style=\"color:#c00000\">adj.</span> met hand, handen van-; met....handen</N></I></F></C><C><F><H><span style=\"color:#009900\">hænd</span></H><I><N><span style=\"color:#c00000\">n.</span> hand; handschrift; wijzer; 4 inch; kaarten i.d. hand van kaartspeler; arbeider; matroos</N></I><I><N><span style=\"color:#c00000\">v.</span> aanreiken, doorgeven, geven; helpen</N></I><I><N><span style=\"color:#c00000\">adj.</span> handig, v.d. hand</N></I></F></C>"
}