{
    "word": "ambition",
    "phonetic": "ambition",
    "type": "n, pl, v",
    "meaning": "честолюбність; владолюбство; амбіція; честолюбний задум;прагнення;мета, об'єкт бажань; мрія;його мрія — стати художником честолюбно прагнути (чогось, до чогось); домагатися (чогось).",
    "details": "<C><F><H><L>ambition</L></H><I><N><strong><x K=\"blue\">1.</x></strong> <span style=\"color:#c00000\">n</span> <strong><x K=\"indigo\">1)</x></strong> честолюбність; владолюбство; амбіція; <strong><x K=\"indigo\">2)</x></strong> <span style=\"color:#c00000\">pl</span> честолюбний задум; <strong><x K=\"indigo\">3)</x></strong> прагнення; <strong><x K=\"indigo\">4)</x></strong> мета, об'єкт бажань; мрія; <x K=\"maroon\">it is his ambition to become an artist</x> його мрія — стати художником<br /> <strong><x K=\"blue\">2.</x></strong> <span style=\"color:#c00000\">v</span> честолюбно прагнути (чогось, до чогось); домагатися (чогось).</N></I></F></C>"
}