{
    "word": "emetic",
    "phonetic": "emetic",
    "type": "n, фарм., adj",
    "meaning": "блювотний засібблювотний;нудотний; огидний.",
    "details": "<C><F><H><L>emetic</L></H><I><N><strong><x K=\"blue\">1.</x></strong> <span style=\"color:#c00000\">n</span> <span style=\"color:#c00000\">фарм.</span> блювотний засіб<br /> <strong><x K=\"blue\">2.</x></strong> <span style=\"color:#c00000\">adj</span> <strong><x K=\"indigo\">1)</x></strong> блювотний; <strong><x K=\"indigo\">2)</x></strong> нудотний; огидний.</N></I></F></C>"
}