{
    "word": "fecundity",
    "phonetic": "fecundity",
    "type": "n",
    "meaning": "родючість;плодовитість, плідність;потік видань;плодотворність, животворна сила.",
    "details": "<C><F><H><L>fecundity</L></H><I><N><span style=\"color:#c00000\">n</span> <strong><x K=\"indigo\">1)</x></strong> родючість; <strong><x K=\"indigo\">2)</x></strong> плодовитість, плідність; <x K=\"maroon\">the fecundity of the publishers</x> потік видань; <strong><x K=\"indigo\">3)</x></strong> плодотворність, животворна сила.</N></I></F></C>"
}