{
    "word": "indicator",
    "phonetic": "indicator",
    "type": "n, хім.",
    "meaning": "індикатор, покажчик; стрілка (циферблата);показник, ознака;лічильник;гідр, покажчик рівня; ♦циферблат; лакмусовий розчин.",
    "details": "<C><F><H><L>indicator</L></H><I><N><span style=\"color:#c00000\">n</span> <strong><x K=\"indigo\">1)</x></strong> індикатор, покажчик; стрілка (циферблата); <strong><x K=\"indigo\">2)</x></strong> показник, ознака; <strong><x K=\"indigo\">3)</x></strong> лічильник; <strong><x K=\"indigo\">4)</x></strong> гідр, покажчик рівня; ♦ <x K=\"maroon\">indicator dial</x> циферблат; <x K=\"maroon\">indicator solution</x> <span style=\"color:#c00000\">хім.</span> лакмусовий розчин.</N></I></F></C>"
}