{
    "word": "jobber",
    "phonetic": "jobber",
    "type": "n",
    "meaning": "людина, що займається випадковою роботою;відрядний працівник;біржовий маклер; комісіонер;оптовий торговець;несумлінний ділок;підприємець, що дає напрокат коней і екіпажі.",
    "details": "<C><F><H><L>jobber</L></H><I><N><span style=\"color:#c00000\">n</span> <strong><x K=\"indigo\">1)</x></strong> людина, що займається випадковою роботою; <strong><x K=\"indigo\">2)</x></strong> відрядний працівник; <strong><x K=\"indigo\">3)</x></strong> біржовий маклер; комісіонер; <strong><x K=\"indigo\">4)</x></strong> оптовий торговець; <strong><x K=\"indigo\">5)</x></strong> несумлінний ділок; <strong><x K=\"indigo\">6)</x></strong> підприємець, що дає напрокат коней і екіпажі.</N></I></F></C>"
}