{
    "word": "lustrum",
    "phonetic": "lustrum",
    "type": "n, pl, тж",
    "meaning": "(lustra)очищувальна жертва (у стародавньому Римі);п'ятиріччя, п'ятирічний період.",
    "details": "<C><F><H><L>lustrum</L></H><I><N><span style=\"color:#c00000\">n</span> (<span style=\"color:#c00000\">pl</span> <span style=\"color:#c00000\">тж</span> lustra) <strong><x K=\"indigo\">1)</x></strong> очищувальна жертва (у стародавньому Римі); <strong><x K=\"indigo\">2)</x></strong> п'ятиріччя, п'ятирічний період.</N></I></F></C>"
}