{
    "word": "pouted",
    "phonetic": "pout",
    "type": "n, іхт., v",
    "meaning": "надутий вигляд; надуті губи; сомик;пташеня; ♦дутисянадувати губи; дутися;витягувати (губи).",
    "details": "<C><F><H><L>pout</L></H><I><N><strong><x K=\"blue\">1.</x></strong> <span style=\"color:#c00000\">n</span> <strong><x K=\"indigo\">1)</x></strong> надутий вигляд; надуті губи; <strong><x K=\"indigo\">2)</x></strong> <span style=\"color:#c00000\">іхт.</span> сомик; <strong><x K=\"indigo\">3)</x></strong> пташеня; ♦ <x K=\"maroon\">to be in the pouts</x> дутися<br /> <strong><x K=\"blue\">2.</x></strong> <span style=\"color:#c00000\">v</span> <strong><x K=\"indigo\">1)</x></strong> надувати губи; дутися; <strong><x K=\"indigo\">2)</x></strong> витягувати (губи).</N></I></F></C>"
}