{
    "word": "toads",
    "phonetic": "toad",
    "type": "n, зоол., знев., adj, розм.",
    "meaning": "жаба; гадина, огидна людина;підлесник, підлабузник;дитинка; жабенятко; ♦місцевий верховода;бути чиїмсь нахлібником жаб'ячий; ротики (квіти).",
    "details": "<C><F><H><L>toad</L></H><I><N><strong><x K=\"blue\">1.</x></strong> <span style=\"color:#c00000\">n</span> <strong><x K=\"indigo\">1)</x></strong> <span style=\"color:#c00000\">зоол.</span> жаба; <strong><x K=\"indigo\">2)</x></strong> <span style=\"color:#c00000\">знев.</span> гадина, огидна людина; <strong><x K=\"indigo\">3)</x></strong> підлесник, підлабузник; <strong><x K=\"indigo\">4)</x></strong> дитинка; жабенятко; ♦ <x K=\"maroon\">the biggest toad in the puddle</x> місцевий верховода; <x K=\"maroon\">to eat smb.'s toads</x> бути чиїмсь нахлібником<br /> <strong><x K=\"blue\">2.</x></strong> <span style=\"color:#c00000\">adj</span> жаб'ячий; <x K=\"maroon\">toad's mouth</x> <span style=\"color:#c00000\">розм.</span> ротики (квіти).</N></I></F></C>"
}