{
    "word": "unsought",
    "phonetic": "unsought",
    "type": "adj",
    "meaning": "одержаний без пошуків; несподіваний;несподівана допомога;непроханий;недосліджений.",
    "details": "<C><F><H><L>unsought</L></H><I><N><span style=\"color:#c00000\">adj</span> <strong><x K=\"indigo\">1)</x></strong> одержаний без пошуків; несподіваний; <x K=\"maroon\">unsought help</x> несподівана допомога; <strong><x K=\"indigo\">2)</x></strong> непроханий; <strong><x K=\"indigo\">3)</x></strong> недосліджений.</N></I></F></C>"
}