{
    "word": "lightnesses",
    "phonetic": "lightnesses",
    "type": "n., Noun",
    "meaning": "1. ہلکا پن۔ سبکی (لاابالی پن)2. بےثباتی۔ بےقراری۔ بےاستقلالی۔ ناپائیداری3. چالاکی۔ پھرتی4. شوخی۔ چنچل پن۔ اچپلاہٹ ۔ مستی۔ روشن ۔ تاباں ۔ مَنسُور ہونے کی حالَت يا کيفِيَت ۔",
    "details": "<C><E>lightnesses</E><F><I><N><Ò>n.<br /> 1. ہلکا پن۔ سبکی (لاابالی پن) <br /> 2. بےثباتی۔ بےقراری۔ بےاستقلالی۔ ناپائیداری <br /> 3. چالاکی۔ پھرتی <br /> 4. شوخی۔ چنچل پن۔ اچپلاہٹ ۔ مستی۔ </Ò></N></I></F><F><I><N><Ò>Noun<br />  روشن ۔ تاباں ۔ مَنسُور ہونے کی حالَت يا کيفِيَت ۔ </Ò></N></I></F></C>"
}