{
    "word": "slur",
    "phonetic": "slɜr /slɜː",
    "type": "n., v.",
    "meaning": "slɜr /slɜːn. mancha, defeito, deficiência; calúnia; difamação; inserção de palavras; gago, tartamudo; modulação (na música)v. difamar, caluniar, botar defeito; falar gaguejando, engolir palavras; modular (na música)",
    "details": "<C><F><H><span style=\"color:#009900\">slɜr /slɜː</span></H><I><N><span style=\"color:#c00000\">n.</span> mancha, defeito, deficiência; calúnia; difamação; inserção de palavras; gago, tartamudo; modulação (na música)</N></I><I><N><span style=\"color:#c00000\">v.</span> difamar, caluniar, botar defeito; falar gaguejando, engolir palavras; modular (na música)</N></I></F></C>"
}