{
    "word": "efflorescing",
    "phonetic": "ef·flo·resce〔L 「피기 시작하다」의 뜻에서〕",
    "type": "vi.",
    "meaning": "《문어》 꽃피다 <문물(文物) 등이> 개화하다, 번영하다 《into》【화학】 풍화(風化)정화(晶化)하다; (땅·벽 등의 표면에서) 소금기가 솟다; 【병리】 발진(發疹)하다",
    "details": "<B>ef·flo·resce</B>〔L 「피기 시작하다」의 뜻에서〕 <font color=\"#008800\">vi.</font><br /><b><br /><font color=\"#FF0000\">1</font> </b> 《문어》 꽃피다<br /><b><br /><font color=\"#FF0000\">2</font> </b> <문물(文物) 등이> 개화하다, 번영하다 《into》<br /><b><br /><font color=\"#FF0000\">3</font> </b>【화학】 풍화(風化)[정화(晶化)]하다; (땅·벽 등의 표면에서) 소금기가 솟다; 【병리】 발진(發疹)하다"
}