{
    "word": "existences",
    "phonetic": "ex·is·tence〔igzíst∂ns〕",
    "type": "n., a.",
    "meaning": "(being) ▶ prove the existence of God 신의 존재를 증명하다 존속, 생존(life) an existence 생존생활 양식, 생활 ▶ lead a happydangerous existence 행복한위험한 생활을 하다 존재물, 실재물, 실체(實體)【철학】 실존(existing) ▷ exíst v.; exístent",
    "details": "<B>ex·is·tence</B>〔igzíst∂ns〕 <font color=\"#008800\">n.</font><br /><b><br /><font color=\"#FF0000\">1</font> </b> <B>[U]</B> <B>존재</B>, 실재, 현존(being)<br /> ▶ prove the existence of God 신의 존재를 증명하다<br /><b><br /><font color=\"#FF0000\">2</font> </b> 존속, 생존(life)<br /><b><br /><font color=\"#FF0000\">3</font> </b> [an existence] 생존[생활] 양식, 생활<br /> ▶ lead a happy[dangerous] existence 행복한[위험한] 생활을 하다<br /><b><br /><font color=\"#FF0000\">4</font> </b> 존재물, 실재물, 실체(實體)<br /><b><br /><font color=\"#FF0000\">5</font> </b>【철학】 실존<br /><B>bring</B>[<B>call</B>] <B>into </B><B>existence </B>생기게 하다, 낳다; 성립시키다 <br /><B>come into existence </B>《문어》 생기다; 성립하다 <br /><B>go</B>[<B>pass</B>]<B> out of existence </B>소멸하다, 없어지다 <br /><B>in</B><B> existence </B>현존의, 존재하는(existing) <br /><B>put ... out of existence </B>절멸시키다, 죽이다<br />▷ exíst v.; exístent <font color=\"#008800\">a.</font>"
}