{
    "word": "holder",
    "phonetic": "hold·er",
    "type": "n.",
    "meaning": "보통 복합어를 이루어▶ a pen holder 펜대 ▶ a cigarette holder 궐련용 물부리 ▶ a record holder 기록 보유자 ▶ a lease holder 차지인(借地人)(유통 증권의) 정당한 소지인",
    "details": "<B>hold·er</B> <font color=\"#008800\">n.</font> [보통 복합어를 이루어] <B>보유자</B>, 소유주, 소지인; 버티는 것, 받침, 그릇, 용기<br /> ▶ a pen holder 펜대<br /> ▶ a cigarette holder 궐련용 물부리<br /> ▶ a record holder 기록 보유자<br /> ▶ a lease holder 차지인(借地人)<br /><B>a holder in due course </B>《미》 (유통 증권의) 정당한 소지인"
}