{
    "word": "informs",
    "phonetic": "알리다, 알려 주다,",
    "type": "vt., vi., a.",
    "meaning": "in·form〔infɔː𝒓m〕〔L 「…에 형태를 부여하다」의 뜻에서〕(⇒ tell 유의어) ▶ 《inform+목+전+명》 《inform+목+ ▶ 《inform+목+ ▶ 《inform+목+ inform oneself로 …에 정통하다, 알다, 분별하다(learn) 《of》 ▶ 《inform+목+전+명》 He informed himself of all necessary procedures. 그는 모든 필요한 절차에 대해 알고 있었다. <작품 등을> 성격특징지우다, <특징·성격 등이> …에 충만하다 채우다, 불어넣다(fill) 《with》 ▶ 《inform+목+전+명》 inform a person with new life …에게 새 생명을 불어넣다<font colorE32E10 size3></font>정보지식를 제공하다; 계발하다 (경찰 등에) 밀고하다, 고발하다 《on, upon, against》 ▶ 《inform+전+명》 You must not inform against him. 그를 고발해서는 안 된다.▷ informàtion n.; infórmative",
    "details": "<B>in·form<SUP style=\"font-size:80%\">1</SUP></B>〔infɔː𝒓m〕〔L 「…에 형태를 부여하다」의 뜻에서〕 <font color=\"#008800\">vt.</font><br /><b><br /><font color=\"#FF0000\">1</font> </b> <B>알리다</B>, 알려 주다, <B>통지하다</B>, 기별하다(⇒ tell [유의어])<br /> ▶ 《inform+목+전+명》 《inform+목+<B>that </B>절》 I informed him of her success.=I informed him that she had been successful. 나는 그에게 그녀의 성공을 알렸다.<br /> ▶ 《inform+목+<B>wh.</B><B> </B>절》 The letter informed me when the man was coming. 그 편지로 그 남자가 언제 오는지를 알았다.<br /> ▶ 《inform+목+<B>wh.</B><B> to </B>do》 Please inform me what to do next. 다음에는 무엇을 해야 할지를 알려 주세요.<br /><b><br /><font color=\"#FF0000\">2</font> </b> [inform oneself로] …에 정통하다, 알다, 분별하다(learn) 《of》<br /> ▶ 《inform+목+전+명》 He informed himself of all necessary procedures. 그는 모든 필요한 절차에 대해 알고 있었다.<br /><b><br /><font color=\"#FF0000\">3</font> </b> <작품 등을> 성격[특징]지우다, <특징·성격 등이> …에 충만하다<br /><b><br /><font color=\"#FF0000\">4</font> </b> 채우다, 불어넣다(fill) 《with》<br /> ▶ 《inform+목+전+명》 inform a person with new life …에게 새 생명을 불어넣다<br /><font color=E32E10 size=3><b>━</b></font> <font color=\"#008800\">vi.</font><br /><b><br /><font color=\"#FF0000\">1</font> </b> 정보[지식]를 제공하다; 계발하다<br /><b><br /><font color=\"#FF0000\">2</font> </b> (경찰 등에) 밀고하다, 고발하다 《on, upon, against》<br /> ▶ 《inform+전+명》 You must not inform against him. 그를 고발해서는 안 된다.<br /><B>be informed of </B>…을 통지받다, …을 들어서 알고 있다 <br /><B>I beg to inform you that </B>…에 관하여 알려 드립니다<br />▷ informàtion n.; infórmative <font color=\"#008800\">a.</font>"
}