{
    "word": "tougher",
    "phonetic": "tough",
    "type": "a., n., vt., a., ad., n., v.",
    "meaning": "(opp. tender, soft); 끈기 있는; <흙>; 꺾어지지 않는 ▶ material as tough as metal and plastic 금속·플라스틱과 같은 정도의 단단한 물질 ▶ tough meat 질긴 고기 ▶ tough clay 차진 점토 《구어》 (hardy); 불굴의; 완고한; <권투 선수 등이> 터프한, 억센(⇒ strong 유의어) ▶ a tough worker 튼튼한 일꾼▶ a tough racket 《속어》 곤란한 일 《미·구어》 불쾌한, <운명 등이> 사나운, 고달픈 ▶ tough luck 불운 믿어지지 않는 ▶ a tough story 믿을 수 없는 이야기 《미·속어》 무법의, 맹렬한, 거센 ▶ a tough customer 거센 사나이 혹심한, 모진, 가차없는, 무서운 ▶ a tough teacher 무서운 선생님 《미·속어》 <언행이> 멋진, 훌륭한() <사람이> 완강한, 냉혹한 () () <font colorE32E10 size3></font>《구어》 악한, 깡패, 부랑자(ruffian); 《특히》 범인 완강강경한 사람<font colorE32E10 size3></font>《미·구어》 참고 견디다 《out》 ▷ tóughen",
    "details": "<B>tough</B> <font color=\"#008800\">a.</font><br /><b><br /><font color=\"#FF0000\">1</font> </b> <B>질긴</B>, 단단한(opp. tender, soft); 끈기 있는; <B>차진</B> <흙>; 꺾어지지 않는<br /> ▶ material as tough as metal and plastic 금속·플라스틱과 같은 정도의 단단한 물질<br /> ▶ tough meat 질긴 고기<br /> ▶ tough clay 차진 점토<br /><b><br /><font color=\"#FF0000\">2</font> </b> 《구어》 <B>튼튼한</B>, <B>강인한</B>(hardy); 불굴의; 완고한; <권투 선수 등이> 터프한, 억센(⇒ strong [유의어])<br /> ▶ a tough worker 튼튼한 일꾼<br /><b><br /><font color=\"#FF0000\">3</font> </b> <B>곤란한</B>, 힘든<br /> ▶ a tough racket 《속어》 곤란한 일<br /><b><br /><font color=\"#FF0000\">4</font> </b> 《미·구어》 불쾌한, <운명 등이> 사나운, 고달픈<br /> ▶ tough luck 불운<br /><b><br /><font color=\"#FF0000\">5</font> </b> 믿어지지 않는<br /> ▶ a tough story 믿을 수 없는 이야기<br /><b><br /><font color=\"#FF0000\">6</font> </b> 《미·속어》 무법의, 맹렬한, 거센<br /> ▶ a tough customer 거센 사나이<br /><b><br /><font color=\"#FF0000\">7</font> </b> 혹심한, 모진, 가차없는, 무서운<br /> ▶ a tough teacher 무서운 선생님<br /><b><br /><font color=\"#FF0000\">8</font> </b> 《미·속어》 <언행이> 멋진, 훌륭한<br />(<B>as</B>) <B>tough as nails </B><사람이> 완강한, 냉혹한<br /> (<B>as</B>) <B>tough as </B>(<B>old</B>) <B>boots</B>[<B>leather</B>] 참을성 있는; 매우 질긴 <br /><B>get tough with </B>…에게 엄하게 굴다 <br /><B>Things are tough. </B>세상살이는 힘들다. <br /><B>Tough! </B>《속어》 설마!<br /><font color=E32E10 size=3><b>━</b></font> <font color=\"#008800\">n.</font><br /><b><br /><font color=\"#FF0000\">1</font> </b> 《구어》 악한, 깡패, 부랑자(ruffian); 《특히》 범인<br /><b><br /><font color=\"#FF0000\">2</font> </b> 완강[강경]한 사람<br /><font color=E32E10 size=3><b>━</b></font> <font color=\"#008800\">vt.</font> 《미·구어》 참고 견디다 《out》<br /> <B>tough it out </B>어려움을 참고 견디다<br /><B>tough·ish </B><font color=\"#008800\">a.</font> <B>tough·ly </B><font color=\"#008800\">ad.</font> <B>tough·ness </B><font color=\"#008800\">n.</font><br />▷ tóughen <font color=\"#008800\">v.</font>"
}